memmod/__init__.py
memmod/libc.py
memmod/memscan.c
memmod/module.py
memmod/monomanager.py
memmod/process.py
memmod/ptracehelper.py
memmod/scripts/__init__.py
memmod/scripts/accessanalyzer.py
memmod/scripts/loadshared.py
memmod/scripts/pointerscanner.py
memmod/scripts/timerhack.py
memmod/memscan.cpython-310-x86_64-linux-gnu.so
libmemmod-0.0.5.dist-info/entry_points.txt
libmemmod-0.0.5.dist-info/LICENSE
libmemmod-0.0.5.dist-info/WHEEL
libmemmod-0.0.5.dist-info/METADATA
libmemmod-0.0.5.dist-info/RECORD
