Metadata-Version: 2.1
Name: libmemmod
Version: 0.0.5
Summary: A library to modify another program's memory.
Home-page: https://github.com/danielfvm/memmod
License: GPL-3.0-only
Keywords: linux,memory,hacking-tools
Author: DanielFvM
Author-email: ds@xxxmail.eu
Classifier: License :: OSI Approved :: GNU General Public License v3 (GPLv3)
Classifier: Programming Language :: Python :: 2
Classifier: Programming Language :: Python :: 2.7
Classifier: Programming Language :: Python :: 3
Classifier: Programming Language :: Python :: 3.10
Classifier: Programming Language :: Python :: 3.4
Classifier: Programming Language :: Python :: 3.5
Classifier: Programming Language :: Python :: 3.6
Classifier: Programming Language :: Python :: 3.7
Classifier: Programming Language :: Python :: 3.8
Classifier: Programming Language :: Python :: 3.9
Requires-Dist: capstone (==4.0.2)
Requires-Dist: pyelftools (>=0.28,<0.29)
Requires-Dist: xlib (>=0.21,<0.22)
Project-URL: Bug Tracker, https://github.com/danielfvm/memmod/issues
Project-URL: Repository, https://github.com/danielfvm/memmod
